Workbook
Name Slicer_Category: #N/A
Name Slicer_Customer_Segment: #N/A
Name Slicer_Region: #N/A

Sheet Raw Data
A1: Transaction_ID | B1: Date | C1: Customer_ID | D1: Customer_Name | E1: Product_ID | F1: Product_Name | G1: Category | H1: Quantity | I1: Unit_Price | J1: Payment_Method | K1: Region | L1: Customer_Segment | M1: Customer_Since | N1: Total_Amount | O1: Month | P1: Year | Q1: Days_As_Customer | R1: Customer_Level
A2: TRX0155 | B2: 45393 | C2: CUST023 | D2: Paul Baker | E2: P009 | F2: Monitor | G2: Electronics | H2: 3 | I2: 249.99 | J2: Cash | K2: Central | L2: Basic | M2: 44425 | N2: 749.97 | O2: =TEXT(CustomerData[[#This Row],[Date]],"mmm") -> Apr | P2: =YEAR(CustomerData[[#This Row],[Date]]) -> 2024 | Q2: =TODAY()-M2 -> 1733 | R2: =IF(N2>=2000,"VIP Customer",IF(N2>=1000,"High Value",IF(N2>=500,"Medium Value","Low Value"))) -> Medium Value
A3: TRX0023 | B3: 45394 | C3: CUST013 | D3: Joseph Jackson | E3: P009 | F3: Monitor | G3: Electronics | H3: 3 | I3: 249.99 | J3: Credit Card | K3: Central | L3: Premium | M3: 44426 | N3: 749.97 | O3: =TEXT(CustomerData[[#This Row],[Date]],"mmm") -> Apr | P3: =YEAR(CustomerData[[#This Row],[Date]]) -> 2024 | Q3: =TODAY()-M3 -> 1732 | R3: =IF(N3>=2000,"VIP Customer",IF(N3>=1000,"High Value",IF(N3>=500,"Medium Value","Low Value"))) -> Medium Value
A4: TRX0139 | B4: 45395 | C4: CUST021 | D4: Kevin Scott | E4: P005 | F4: Blender | G4: Appliances | H4: 3 | I4: 59.99 | J4: PayPal | K4: South | L4: Standard | M4: 44427 | N4: 179.97 | O4: =TEXT(CustomerData[[#This Row],[Date]],"mmm") -> Apr | P4: =YEAR(CustomerData[[#This Row],[Date]]) -> 2024 | Q4: =TODAY()-M4 -> 1731 | R4: =IF(N4>=2000,"VIP Customer",IF(N4>=1000,"High Value",IF(N4>=500,"Medium Value","Low Value"))) -> Low Value
A5: TRX0043 | B5: 45396 | C5: CUST046 | D5: Kathleen Bennett | E5: P005 | F5: Blender | G5: Appliances | H5: 3 | I5: 59.99 | J5: Cash | K5: North | L5: Premium | M5: 44428 | N5: 179.97 | O5: =TEXT(CustomerData[[#This Row],[Date]],"mmm") -> Apr | P5: =YEAR(CustomerData[[#This Row],[Date]]) -> 2024 | Q5: =TODAY()-M5 -> 1730 | R5: =IF(N5>=2000,"VIP Customer",IF(N5>=1000,"High Value",IF(N5>=500,"Medium Value","Low Value"))) -> Low Value
A6: TRX0212 | B6: 45397 | C6: CUST003 | D6: Michael Brown | E6: P008 | F6: Bookshelf | G6: Furniture | H6: 5 | I6: 149.99 | J6: Credit Card | K6: North | L6: Premium | M6: 44429 | N6: 749.95 | O6: =TEXT(CustomerData[[#This Row],[Date]],"mmm") -> Apr | P6: =YEAR(CustomerData[[#This Row],[Date]]) -> 2024 | Q6: =TODAY()-M6 -> 1729 | R6: =IF(N6>=2000,"VIP Customer",IF(N6>=1000,"High Value",IF(N6>=500,"Medium Value","Low Value"))) -> Medium Value
A7: TRX0092 | B7: 45398 | C7: CUST024 | D7: Dorothy Nelson | E7: P005 | F7: Blender | G7: Appliances | H7: 2 | I7: 59.99 | J7: Cash | K7: West | L7: Standard | M7: 44430 | N7: 119.98 | O7: =TEXT(CustomerData[[#This Row],[Date]],"mmm") -> Apr | P7: =YEAR(CustomerData[[#This Row],[Date]]) -> 2024 | Q7: =TODAY()-M7 -> 1728 | R7: =IF(N7>=2000,"VIP Customer",IF(N7>=1000,"High Value",IF(N7>=500,"Medium Value","Low Value"))) -> Low Value
A8: TRX0193 | B8: 45399 | C8: CUST024 | D8: Dorothy Nelson | E8: P003 | F8: Headphones | G8: Electronics | H8: 5 | I8: 149.99 | J8: Credit Card | K8: Central | L8: Standard | M8: 44431 | N8: 749.95 | O8: =TEXT(CustomerData[[#This Row],[Date]],"mmm") -> Apr | P8: =YEAR(CustomerData[[#This Row],[Date]]) -> 2024 | Q8: =TODAY()-M8 -> 1727 | R8: =IF(N8>=2000,"VIP Customer",IF(N8>=1000,"High Value",IF(N8>=500,"Medium Value","Low Value"))) -> Medium Value
A9: TRX0240 | B9: 45400 | C9: CUST017 | D9: Charles Allen | E9: P005 | F9: Blender | G9: Appliances | H9: 3 | I9: 59.99 | J9: Debit Card | K9: South | L9: Basic | M9: 44432 | N9: 179.97 | O9: =TEXT(CustomerData[[#This Row],[Date]],"mmm") -> Apr | P9: =YEAR(CustomerData[[#This Row],[Date]]) -> 2024 | Q9: =TODAY()-M9 -> 1726 | R9: =IF(N9>=2000,"VIP Customer",IF(N9>=1000,"High Value",IF(N9>=500,"Medium Value","Low Value"))) -> Low Value
A10: TRX0135 | B10: 45401 | C10: CUST009 | D10: Robert Thomas | E10: P001 | F10: Laptop | G10: Electronics | H10: 3 | I10: 899.99 | J10: PayPal | K10: East | L10: Standard | M10: 44433 | N10: 2699.97 | O10: =TEXT(CustomerData[[#This Row],[Date]],"mmm") -> Apr | P10: =YEAR(CustomerData[[#This Row],[Date]]) -> 2024 | Q10: =TODAY()-M10 -> 1725 | R10: =IF(N10>=2000,"VIP Customer",IF(N10>=1000,"High Value",IF(N10>=500,"Medium Value","Low Value"))) -> VIP Customer
A11: TRX0185 | B11: 45402 | C11: CUST026 | D11: Karen Hill | E11: P005 | F11: Blender | G11: Appliances | H11: 3 | I11: 59.99 | J11: Cash | K11: West | L11: Premium | M11: 44434 | N11: 179.97 | O11: =TEXT(CustomerData[[#This Row],[Date]],"mmm") -> Apr | P11: =YEAR(CustomerData[[#This Row],[Date]]) -> 2024 | Q11: =TODAY()-M11 -> 1724 | R11: =IF(N11>=2000,"VIP Customer",IF(N11>=1000,"High Value",IF(N11>=500,"Medium Value","Low Value"))) -> Low Value
A12: TRX0138 | B12: 45403 | C12: CUST022 | D12: Susan Green | E12: P008 | F12: Bookshelf | G12: Furniture | H12: 1 | I12: 149.99 | J12: Credit Card | K12: West | L12: Standard | M12: 44435 | N12: 149.99 | O12: =TEXT(CustomerData[[#This Row],[Date]],"mmm") -> Apr | P12: =YEAR(CustomerData[[#This Row],[Date]]) -> 2024 | Q12: =TODAY()-M12 -> 1723 | R12: =IF(N12>=2000,"VIP Customer",IF(N12>=1000,"High Value",IF(N12>=500,"Medium Value","Low Value"))) -> Low Value
A13: TRX0209 | B13: 45404 | C13: CUST046 | D13: Kathleen Bennett | E13: P008 | F13: Bookshelf | G13: Furniture | H13: 5 | I13: 149.99 | J13: Debit Card | K13: North | L13: Basic | M13: 44436 | N13: 749.95 | O13: =TEXT(CustomerData[[#This Row],[Date]],"mmm") -> Apr | P13: =YEAR(CustomerData[[#This Row],[Date]]) -> 2024 | Q13: =TODAY()-M13 -> 1722 | R13: =IF(N13>=2000,"VIP Customer",IF(N13>=1000,"High Value",IF(N13>=500,"Medium Value","Low Value"))) -> Medium Value
... A251: TRX0064 | B251: 45642 | C251: CUST031 | D251: Steven Turner | E251: P010 | F251: Keyboard | G251: Electronics | H251: 3 | I251: 89.99 | J251: Debit Card | K251: North | L251: Premium | M251: 44674 | N251: 269.97 | O251: =TEXT(CustomerData[[#This Row],[Date]],"mmm") -> Dec | P251: =YEAR(CustomerData[[#This Row],[Date]]) -> 2024 | Q251: =TODAY()-M251 -> 1484 | R251: =IF(N251>=2000,"VIP Customer",IF(N251>=1000,"High Value",IF(N251>=500,"Medium Value","Low Value"))) -> Low Value

Sheet Analysis
B1: ANALYSIS SHEET – Formulas, KPIs & Data Insights
B3: Date & Time Functions section | E3: GroupBy – High Value Customers | J3: Product Analysis – Most Purchased Products
B4: Today's Date | C4: =TODAY() -> 46158 | E4: Customer Name | F4: Total Revenue | G4: No. of Orders | H4: Avg Order Value | J4: Product Name | K4: Total Revenue | L4: Qty Sold | M4: No. of Orders
B5: Days Of Data | C5: =DATEDIF(MIN('Raw Data'!B2:B251), TODAY(), "D") -> 765 | E5: Mark Carter | F5: =SUMIF('Raw Data'!D:D, E5, 'Raw Data'!N:N) -> 15659.65 | G5: =COUNTIF('Raw Data'!D:D, E5) -> 12 | H5: =IFERROR(F5/G5, 0) -> 1304.9708 | J5: Laptop | K5: =SUMIF('Raw Data'!F:F, J5, 'Raw Data'!N:N) -> 67499.25 | L5: =SUMIF('Raw Data'!F:F, J5, 'Raw Data'!H:H) -> 75 | M5: =COUNTIF('Raw Data'!F:F, J5) -> 24
B6: End of Current Month | C6: =EOMONTH(TODAY(),0) -> 46173 | E6: Edward Mitchell | F6: =SUMIF('Raw Data'!D:D, E6, 'Raw Data'!N:N) -> 11919.77 | G6: =COUNTIF('Raw Data'!D:D, E6) -> 6 | H6: =IFERROR(F6/G6, 0) -> 1986.6283 | J6: Smartphone | K6: =SUMIF('Raw Data'!F:F, J6, 'Raw Data'!N:N) -> 67199.04 | L6: =SUMIF('Raw Data'!F:F, J6, 'Raw Data'!H:H) -> 96 | M6: =COUNTIF('Raw Data'!F:F, J6) -> 31
B7: Current Timestamp | C7: =NOW() -> 46158.466 | E7: Karen Hill | F7: =SUMIF('Raw Data'!D:D, E7, 'Raw Data'!N:N) -> 8009.77 | G7: =COUNTIF('Raw Data'!D:D, E7) -> 8 | H7: =IFERROR(F7/G7, 0) -> 1001.2212 | J7: Headphones | K7: =SUMIF('Raw Data'!F:F, J7, 'Raw Data'!N:N) -> 7049.53 | L7: =SUMIF('Raw Data'!F:F, J7, 'Raw Data'!H:H) -> 47 | M7: =COUNTIF('Raw Data'!F:F, J7) -> 16
E8: Barbara Young | F8: =SUMIF('Raw Data'!D:D, E8, 'Raw Data'!N:N) -> 10649.8 | G8: =COUNTIF('Raw Data'!D:D, E8) -> 5 | H8: =IFERROR(F8/G8, 0) -> 2129.96 | J8: Coffee Maker | K8: =SUMIF('Raw Data'!F:F, J8, 'Raw Data'!N:N) -> 3119.61 | L8: =SUMIF('Raw Data'!F:F, J8, 'Raw Data'!H:H) -> 39 | M8: =COUNTIF('Raw Data'!F:F, J8) -> 14
E9: Joseph Jackson | F9: =SUMIF('Raw Data'!D:D, E9, 'Raw Data'!N:N) -> 6949.84 | G9: =COUNTIF('Raw Data'!D:D, E9) -> 5 | H9: =IFERROR(F9/G9, 0) -> 1389.968 | J9: Blender | K9: =SUMIF('Raw Data'!F:F, J9, 'Raw Data'!N:N) -> 5219.13 | L9: =SUMIF('Raw Data'!F:F, J9, 'Raw Data'!H:H) -> 87 | M9: =COUNTIF('Raw Data'!F:F, J9) -> 29
B10: KPI Metrics – Key Performance Indicators | E10: Paul Baker | F10: =SUMIF('Raw Data'!D:D, E10, 'Raw Data'!N:N) -> 8309.74 | G10: =COUNTIF('Raw Data'!D:D, E10) -> 8 | H10: =IFERROR(F10/G10, 0) -> 1038.7175 | J10: Office Chair | K10: =SUMIF('Raw Data'!F:F, J10, 'Raw Data'!N:N) -> 10399.48 | L10: =SUMIF('Raw Data'!F:F, J10, 'Raw Data'!H:H) -> 52 | M10: =COUNTIF('Raw Data'!F:F, J10) -> 15
B11: Total Revenue | C11: =SUM('Raw Data'!N:N) -> 229192.47 | E11: Betty Campbell | F11: =SUMIF('Raw Data'!D:D, E11, 'Raw Data'!N:N) -> 5649.84 | G11: =COUNTIF('Raw Data'!D:D, E11) -> 5 | H11: =IFERROR(F11/G11, 0) -> 1129.968 | J11: Desk | K11: =SUMIF('Raw Data'!F:F, J11, 'Raw Data'!N:N) -> 23399.22 | L11: =SUMIF('Raw Data'!F:F, J11, 'Raw Data'!H:H) -> 78 | M11: =COUNTIF('Raw Data'!F:F, J11) -> 26
B12: Total Transactions | C12: =COUNTA('Raw Data'!A:A) -> 251 | E12: Helen Roberts | F12: =SUMIF('Raw Data'!D:D, E12, 'Raw Data'!N:N) -> 6459.79 | G12: =COUNTIF('Raw Data'!D:D, E12) -> 7 | H12: =IFERROR(F12/G12, 0) -> 922.82714 | J12: Bookshelf | K12: =SUMIF('Raw Data'!F:F, J12, 'Raw Data'!N:N) -> 15298.98 | L12: =SUMIF('Raw Data'!F:F, J12, 'Raw Data'!H:H) -> 102 | M12: =COUNTIF('Raw Data'!F:F, J12) -> 35
B13: Average Order Value | C13: =AVERAGE('Raw Data'!N:N) -> 916.76988 | E13: Daniel King | F13: =SUMIF('Raw Data'!D:D, E13, 'Raw Data'!N:N) -> 7309.8 | G13: =COUNTIF('Raw Data'!D:D, E13) -> 7 | H13: =IFERROR(F13/G13, 0) -> 1044.2571 | J13: Monitor | K13: =SUMIF('Raw Data'!F:F, J13, 'Raw Data'!N:N) -> 21999.12 | L13: =SUMIF('Raw Data'!F:F, J13, 'Raw Data'!H:H) -> 88 | M13: =COUNTIF('Raw Data'!F:F, J13) -> 26
B14: Max Single Order | C14: =MAX('Raw Data'!N:N) -> 4499.95 | E14: Lawrence Reed | F14: =SUMIF('Raw Data'!D:D, E14, 'Raw Data'!N:N) -> 6989.77 | G14: =COUNTIF('Raw Data'!D:D, E14) -> 8 | H14: =IFERROR(F14/G14, 0) -> 873.72125 | J14: Keyboard | K14: =SUMIF('Raw Data'!F:F, J14, 'Raw Data'!N:N) -> 8009.11 | L14: =SUMIF('Raw Data'!F:F, J14, 'Raw Data'!H:H) -> 89 | M14: =COUNTIF('Raw Data'!F:F, J14) -> 34
B15: Min Single Order | C15: =MIN('Raw Data'!N:N) -> 59.99 | E15: Peter Richardson | F15: =SUMIF('Raw Data'!D:D, E15, 'Raw Data'!N:N) -> 5949.85 | G15: =COUNTIF('Raw Data'!D:D, E15) -> 5 | H15: =IFERROR(F15/G15, 0) -> 1189.97
B16: Total Qty Sold | C16: =SUM('Raw Data'!H:H) -> 753 | E16: Harry Morgan | F16: =SUMIF('Raw Data'!D:D, E16, 'Raw Data'!N:N) -> 5519.89 | G16: =COUNTIF('Raw Data'!D:D, E16) -> 4 | H16: =IFERROR(F16/G16, 0) -> 1379.9725
B17: Unique Customers | C17: {=SUMPRODUCT(1/COUNTIF('Raw Data'!C2:C251,'Raw Data'!C2:C251))} -> 50 | E17: Dorothy Nelson | F17: =SUMIF('Raw Data'!D:D, E17, 'Raw Data'!N:N) -> 8269.79 | G17: =COUNTIF('Raw Data'!D:D, E17) -> 6 | H17: =IFERROR(F17/G17, 0) -> 1378.2983
B18: Premium Revenue | C18: =SUMIF('Raw Data'!L:L,"Premium",'Raw Data'!N:N) -> 84657.12 | E18: Gerald Murphy | F18: =SUMIF('Raw Data'!D:D, E18, 'Raw Data'!N:N) -> 6379.87 | G18: =COUNTIF('Raw Data'!D:D, E18) -> 4 | H18: =IFERROR(F18/G18, 0) -> 1594.9675
B19: Electronics Revenue | C19: =SUMIF('Raw Data'!G:G,"Electronics",'Raw Data'!N:N) -> 171756.05 | E19: Patricia Moore | F19: =SUMIF('Raw Data'!D:D, E19, 'Raw Data'!N:N) -> 9799.73 | G19: =COUNTIF('Raw Data'!D:D, E19) -> 8 | H19: =IFERROR(F19/G19, 0) -> 1224.9662
B20: Furniture Revenue | C20: =SUMIF('Raw Data'!G:G,"Furniture",'Raw Data'!N:N) -> 49097.68
B21: Appliances Revenue | C21: =SUMIF('Raw Data'!G:G,"Appliances",'Raw Data'!N:N) -> 8338.74
B23: What-If Analysis – Scenario Manager | F23: Linear Regression – Quantity vs Total Amount
B24: Scenario | C24: Growth Rate | D24: Projected Revenue | F24: SUMMARY OUTPUT
B25: Pessimistic | C25: 0.05 | D25: =C11*(1+C25) -> 240652.09
B26: Base Case | C26: 0.12 | D26: =C11*(1+C26) -> 256695.57 | F26: Regression Statistics
B27: Optimistic | C27: 0.2 | D27: =C11*(1+C27) -> 275030.96 | F27: Multiple R | G27: 0.45809869
F28: R Square | G28: 0.20985441
F29: Adjusted R Square | G29: 0.20665544
F30: Standard Error | G30: 921.40854
F31: Observations | G31: 249
F33: ANOVA
G34: df | H34: SS | I34: MS | J34: F | K34: Significance F
F35: Regression | G35: 1 | H35: 55694513 | I35: 55694513 | J35: 65.60062 | K35: 2.5391277e-14
F36: Residual | G36: 247 | H36: 2.0970144e+08 | I36: 848993.7
F37: Total | G37: 248 | H37: 2.6539596e+08
G39: Coefficients | H39: Standard Error | I39: t Stat | J39: P-value | K39: Lower 95% | L39: Upper 95% | M39: Lower 95.0% | N39: Upper 95.0%
F40: Intercept | G40: -148.18856 | H40: 143.94399 | I40: -1.0294877 | J40: 0.30425761 | K40: -431.70277 | L40: 135.32564 | M40: -431.70277 | N40: 135.32564
F41: 3 | G41: 353.7886 | H41: 43.680728 | I41: 8.0994209 | J41: 2.5391277e-14 | K41: 267.7544 | L41: 439.82281 | M41: 267.7544 | N41: 439.82281

Sheet Visualizations
C1: VISUALIZATIONS – Charts & Graphs for Data Intelligence Dashboard
C3: Revenue by Category | F3: Revenue by Region | I3: Revenue by Payment Method | L3: Top 10 Customers by Revenue | O3: Monthly Revenue Trend
C4: Row Labels | D4: Sum of Total_Amount | F4: Row Labels | G4: Sum of Total_Amount | I4: Row Labels | J4: Sum of Total_Amount | L4: Row Labels | M4: Sum of Total_Amount | O4: Row Labels | P4: Sum of Total_Amount
C5: Appliances | D5: 8338.74 | F5: Central | G5: 41288.34 | I5: Cash | J5: 57427.79 | L5: Paul Baker | M5: 8309.74 | O5: Apr | P5: 17419.38
C6: Electronics | D6: 171756.05 | F6: East | G6: 59288.39 | I6: Credit Card | J6: 61447.96 | L6: Patricia Moore | M6: 9799.73 | O6: May | P6: 32708.93
C7: Furniture | D7: 49097.68 | F7: North | G7: 50808.31 | I7: Debit Card | J7: 52118.31 | L7: Mark Carter | M7: 15659.65 | O7: Jun | P7: 20609.28
C8: Grand Total | D8: 229192.47 | F8: South | G8: 36398.75 | I8: PayPal | J8: 58198.41 | L8: Lawrence Reed | M8: 6989.77 | O8: Jul | P8: 25599.11
F9: West | G9: 41408.68 | I9: Grand Total | J9: 229192.47 | L9: Karen Hill | M9: 8009.77 | O9: Aug | P9: 32479.07
F10: Grand Total | G10: 229192.47 | L10: Joseph Jackson | M10: 6949.84 | O10: Sep | P10: 28489.09
L11: Edward Mitchell | M11: 11919.77 | O11: Oct | P11: 28939.02
L12: Dorothy Nelson | M12: 8269.79 | O12: Nov | P12: 27369.05
L13: Daniel King | M13: 7309.8 | O13: Dec | P13: 15579.54
L14: Barbara Young | M14: 10649.8
L15: Grand Total | M15: 93867.66

Sheet Dashboard
C3: 📊 DATA INTELLIGENCE DASHBOARD
C6: Customer Transaction Analysis | Auto-Updated: =TODAY() | Report Period: Apr 2024 – Aug 2024
C8: Total Revenue | H8: Total Transactions | M8: Unique Customers | R8: Avg Order Value
C10: =SUM('Raw Data'!N:N) -> 229192.47 | H10: =COUNTA('Raw Data'!A:A) -> 251 | M10: {=SUMPRODUCT(1/COUNTIF('Raw Data'!C2:C251,'Raw Data'!C2:C251))} -> 50 | R10: =AVERAGE('Raw Data'!N:N) -> 916.76988

Sheet Sheet1
